{
  "candidate_id": "QA_and_Regulatory_Penugonda_Roopa",
  "name": "Roopa Penugonda, M.S., B.Tech",
  "role_category": "QA & Regulatory",
  "titles": [
    "Independent Consultant",
    "CSV Engineer",
    "CQV Engineer",
    "QA Validation Engineer",
    "Validation Engineer"
  ],
  "skills": [
    {
      "name": "go",
      "level": "mentioned"
    },
    {
      "name": "gcp",
      "level": "mentioned"
    },
    {
      "name": "ai",
      "level": "mentioned"
    },
    {
      "name": "testing",
      "level": "mentioned"
    },
    {
      "name": "qa",
      "level": "mentioned"
    },
    {
      "name": "quality assurance",
      "level": "mentioned"
    },
    {
      "name": "validation",
      "level": "mentioned"
    },
    {
      "name": "regulatory",
      "level": "mentioned"
    },
    {
      "name": "medical device",
      "level": "mentioned"
    },
    {
      "name": "gmp",
      "level": "mentioned"
    },
    {
      "name": "fda",
      "level": "mentioned"
    },
    {
      "name": "iso 13485",
      "level": "mentioned"
    },
    {
      "name": "iso",
      "level": "mentioned"
    },
    {
      "name": "capa",
      "level": "mentioned"
    },
    {
      "name": "csv",
      "level": "mentioned"
    },
    {
      "name": "21 cfr part 11",
      "level": "mentioned"
    },
    {
      "name": "audit",
      "level": "mentioned"
    },
    {
      "name": "compliance",
      "level": "mentioned"
    },
    {
      "name": "agile",
      "level": "mentioned"
    },
    {
      "name": "lean",
      "level": "mentioned"
    }
  ],
  "experience_years": 0,
  "location": null,
  "work_authorization": "EAD",
  "resume_snippet": "Roopa Penugonda, M.S., B.Tech  PROFESSIONAL SUMMARY:\t  8+ years of professional experience in the capacity of Validation Engineer and Quality Assurance in the Pharmaceutical and Life Sciences Industries. Vast working experience in different document management systems like Veeva Vault, Asset Management, Electronic Document Management System (EDMS), SharePoint. Authored and Reviewed SDLC deliverables which include Compliance Analysis, Risk Assessment, Requirements Specifications. Authored and Re",
  "email": null,
  "phone": null,
  "full_text_length": 11606,
  "source_file": "AVS CV's/QA & Regulatory/Penugonda, Roopa/Penugonda, Roopa AVS CV 061225.docx",
  "parsed_date": "2025-10-15T12:34:23.882221"
}